troposphere_crunch/__init__.py
troposphere_crunch/consts.py
troposphere_crunch/main.py
troposphere_crunch/types.py
troposphere_crunch-1.0.2.dist-info/entry_points.txt
troposphere_crunch-1.0.2.dist-info/LICENSE
troposphere_crunch-1.0.2.dist-info/WHEEL
troposphere_crunch-1.0.2.dist-info/METADATA
troposphere_crunch-1.0.2.dist-info/RECORD
