Metadata-Version: 2.1
Name: troposphere_crunch
Version: 1.0.2
Summary: A tool to compile and (optionally) deploy Troposphere templates with AWS CLI and a very opinionated structure.
Home-page: https://github.com/klardotsh/troposphere-crunch
License: UNKNOWN
Author: Josh Klar
Author-email: josh@klar.sh
Classifier: License :: OSI Approved :: MIT License
Requires-Dist: troposphere
Requires-Dist: toml
Requires-Dist: tqdm
Provides-Extra: .none
